GstTimelapseRtspServer/Generators.py
GstTimelapseRtspServer/Servers.py
GstTimelapseRtspServer/__init__.py
Gstreamer_Timelapse_RTSP_Server-0.0.1.post1.dist-info/DESCRIPTION.rst
Gstreamer_Timelapse_RTSP_Server-0.0.1.post1.dist-info/METADATA
Gstreamer_Timelapse_RTSP_Server-0.0.1.post1.dist-info/RECORD
Gstreamer_Timelapse_RTSP_Server-0.0.1.post1.dist-info/WHEEL
Gstreamer_Timelapse_RTSP_Server-0.0.1.post1.dist-info/metadata.json
Gstreamer_Timelapse_RTSP_Server-0.0.1.post1.dist-info/top_level.txt
